pydeclares/__init__.py
pydeclares/declares.py
pydeclares/defines.py
pydeclares/exceptions.py
pydeclares/typing.py
pydeclares/utils.py
pydeclares/variables.py
pydeclares/marshals/__init__.py
pydeclares/marshals/exceptions.py
pydeclares/marshals/json.py
pydeclares/marshals/xml.py
tests/__init__.py
tests/test_declares.py
tests/test_serializes.py
tests/test_vars.py
tests/marshals/__init__.py
tests/marshals/test_json.py
tests/marshals/test_xml.py
pydeclares-1.0.3.dist-info/METADATA
pydeclares-1.0.3.dist-info/WHEEL
pydeclares-1.0.3.dist-info/top_level.txt
pydeclares-1.0.3.dist-info/RECORD
