Metadata-Version: 2.1
Name: pydeclares
Version: 1.0.3
Summary: A tool for provide format and serialize support to json, xml, form data and query string.
Home-page: https://github.com/phona/pydeclares
Author: heweitao
Author-email: 675428202@qq.com
License: UNKNOWN
Platform: UNKNOWN
Classifier: Programming Language :: Python :: 3
Classifier: License :: OSI Approved :: MIT License
Classifier: Operating System :: OS Independent
Requires-Python: >=3.5
Requires-Dist: typing-extensions (>=3.7.2) ; python_version < "3.7"
